MANIFEST.in
README
hc-vcs.py
hcvcs.py
setup.py
hcvcs.egg-info/PKG-INFO
hcvcs.egg-info/SOURCES.txt
hcvcs.egg-info/dependency_links.txt
hcvcs.egg-info/requires.txt
hcvcs.egg-info/top_level.txt