Metadata-Version: 1.0
Name: hcvcs
Version: 1.0.2
Summary: VERITAS Cluster Server Health Check
Home-page: https://github.com/jonEbird/hc-vcs
Author: Jon Miller
Author-email: jonEbird@gmail.com
License: LGPL
Download-URL: http://jonebird.com/downloads/hcvcs-1.0.2.tar.gz
Keywords: veritas,VCS,cluster
Platform: Posix; MacOS X
Classifier: Programming Language :: Python
Classifier: Development Status :: 4 - Beta
Classifier: Environment :: Other Environment
Classifier: Intended Audience :: System Administrators
Classifier: License :: OSI Approved :: GNU Library or Lesser General Public License (LGPL)
Classifier: Operating System :: POSIX
Classifier: Topic :: System :: Clustering
